CHANGES.txt
CONTRIBUTORS.txt
MANIFEST.in
README.rst
TODO.txt
base.cfg
buildout.cfg
setup.py
test-4.0.x.cfg
test-4.1.x.cfg
test-4.2.x.cfg
test-4.3.x.cfg
test-5.x.cfg
travis-4.2.x.cfg
travis-4.3.x.cfg
travis-5.0.x.cfg
Products/__init__.py
Products.ATVocabularyManager.egg-info/PKG-INFO
Products.ATVocabularyManager.egg-info/SOURCES.txt
Products.ATVocabularyManager.egg-info/dependency_links.txt
Products.ATVocabularyManager.egg-info/entry_points.txt
Products.ATVocabularyManager.egg-info/namespace_packages.txt
Products.ATVocabularyManager.egg-info/not-zip-safe
Products.ATVocabularyManager.egg-info/requires.txt
Products.ATVocabularyManager.egg-info/top_level.txt
Products/ATVocabularyManager/Makefile
Products/ATVocabularyManager/__init__.py
Products/ATVocabularyManager/config.py
Products/ATVocabularyManager/configure.zcml
Products/ATVocabularyManager/event.py
Products/ATVocabularyManager/importexport.py
Products/ATVocabularyManager/interfaces.py
Products/ATVocabularyManager/namedvocabulary.py
Products/ATVocabularyManager/rebuild_i18n.sh
Products/ATVocabularyManager/setuphandlers.py
Products/ATVocabularyManager/tool.gif
Products/ATVocabularyManager/upgrades.py
Products/ATVocabularyManager/upgrades.zcml
Products/ATVocabularyManager/doc/__init__.py
Products/ATVocabularyManager/doc/search_treevocabulary.txt
Products/ATVocabularyManager/doc/simplevocabulary.txt
Products/ATVocabularyManager/locales/atvocabularymanager.pot
Products/ATVocabularyManager/locales/plone.pot
Products/ATVocabularyManager/locales/cs/LC_MESSAGES/atvocabularymanager.mo
Products/ATVocabularyManager/locales/cs/LC_MESSAGES/atvocabularymanager.po
Products/ATVocabularyManager/locales/cs/LC_MESSAGES/plone.mo
Products/ATVocabularyManager/locales/cs/LC_MESSAGES/plone.po
Products/ATVocabularyManager/locales/da/LC_MESSAGES/atvocabularymanager.mo
Products/ATVocabularyManager/locales/da/LC_MESSAGES/atvocabularymanager.po
Products/ATVocabularyManager/locales/da/LC_MESSAGES/plone.mo
Products/ATVocabularyManager/locales/da/LC_MESSAGES/plone.po
Products/ATVocabularyManager/locales/de/LC_MESSAGES/atvocabularymanager.mo
Products/ATVocabularyManager/locales/de/LC_MESSAGES/atvocabularymanager.po
Products/ATVocabularyManager/locales/de/LC_MESSAGES/plone.mo
Products/ATVocabularyManager/locales/de/LC_MESSAGES/plone.po
Products/ATVocabularyManager/locales/es/LC_MESSAGES/atvocabularymanager.mo
