Metadata-Version: 1.1
Name: Products.ATVocabularyManager
Version: 1.6.7
Summary: Vocabulary library Plone. Central, Pluggable, TTW, with IMS VDEX Support
Home-page: https://github.com/collective/Products.ATVocabularyManager
Author: BlueDynamics Alliance
Author-email: dev@bluedynamics.com
License: UNKNOWN
Keywords: Plone Vocabulary Manager Zope IMS VDEX Tree Taxonomy Onthology
Platform: UNKNOWN
Classifier: Framework :: Plone
Classifier: Framework :: Plone :: 3.3
Classifier: Framework :: Plone :: 4.0
Classifier: Framework :: Plone :: 4.1
Classifier: Framework :: Plone :: 4.2
Classifier: Framework :: Plone :: 4.3
Classifier: Framework :: Plone :: 5.0
Classifier: Framework :: Zope2
Classifier: Programming Language :: Python
